{"schema_version":"geox_mcft00_negative_fixture_part_v1","phase":"MCFT-00","status":"FROZEN","acceptance_status":"PENDING","part_number":6,"fixture_count":10,"fixtures":[{"fixture_id":"NEG_RANDOM_UUID_IDENTITY","test_kind":"MUTATION","target":"package","mutations":[{"op":"set","path":"reality.binding_id","value":"550e8400-e29b-41d4-a716-446655440000"}],"expected_reason_code":"RANDOM_IDENTITY_FORBIDDEN","expected_stage":"DETERMINISM_VALIDATION","expected_no_write":true},{"fixture_id":"NEG_CREATED_AT_HASH","test_kind":"MUTATION","target":"package","mutations":[{"op":"set","path":"reality.semantic_payload.created_at","value":"2026-01-01T00:00:00Z"}],"expected_reason_code":"FORBIDDEN_HASH_INPUT_CREATED_AT","expected_stage":"DETERMINISM_VALIDATION","expected_no_write":true},{"fixture_id":"NEG_ABSOLUTE_PATH_HASH","test_kind":"MUTATION","target":"package","mutations":[{"op":"set","path":"reality.semantic_payload.source_path","value":"C:\\temp\\checkout\\binding.json"}],"expected_reason_code":"FORBIDDEN_HASH_INPUT_ABSOLUTE_PATH","expected_stage":"DETERMINISM_VALIDATION","expected_no_write":true},{"fixture_id":"NEG_IDEMPOTENCY_CONFLICT","test_kind":"ID_CONFLICT","target":"package","mutations":[],"expected_reason_code":"IDEMPOTENCY_CONFLICT","expected_stage":"DETERMINISM_VALIDATION","expected_no_write":true},{"fixture_id":"NEG_BINDING_LINEAGE_ID","test_kind":"MUTATION","target":"package","mutations":[{"op":"set","path":"reality.lineage_id","value":"lin_bad"}],"expected_reason_code":"REALITY_BINDING_LINEAGE_ID_FORBIDDEN","expected_stage":"VERSIONING_VALIDATION","expected_no_write":true},{"fixture_id":"NEG_BINDING_REVISION_ID","test_kind":"MUTATION","target":"package","mutations":[{"op":"set","path":"reality.revision_id","value":"rev_bad"}],"expected_reason_code":"REALITY_BINDING_REVISION_ID_FORBIDDEN","expected_stage":"VERSIONING_VALIDATION","expected_no_write":true},{"fixture_id":"NEG_BINDING_E_OPERATION","test_kind":"MUTATION","target":"package","mutations":[{"op":"set","path":"reality.semantic_payload.versioning_contract.runtime_operations","value":["E1_DECLARE_REVISION"]}],"expected_reason_code":"REALITY_BINDING_RUNTIME_REVISION_FORBIDDEN","expected_stage":"VERSIONING_VALIDATION","expected_no_write":true},{"fixture_id":"NEG_BINDING_ACTIVE_SWITCH","test_kind":"MUTATION","target":"package","mutations":[{"op":"set","path":"reality.semantic_payload.versioning_contract.switches_active_lineage","value":true}],"expected_reason_code":"REALITY_BINDING_ACTIVE_LINEAGE_SWITCH_FORBIDDEN","expected_stage":"VERSIONING_VALIDATION","expected_no_write":true},{"fixture_id":"NEG_BINDING_WRITTEN_FACTS","test_kind":"MUTATION","target":"package","mutations":[{"op":"set","path":"reality.canonical_persistence","value":true}],"expected_reason_code":"REALITY_BINDING_CANONICAL_PERSISTENCE_FORBIDDEN","expected_stage":"CANONICAL_BOUNDARY","expected_no_write":true},{"fixture_id":"NEG_BINDING_ACTIVE_CONFIG","test_kind":"MUTATION","target":"package","mutations":[{"op":"set","path":"reality.active_runtime_config_ref","value":"cfg_bad"}],"expected_reason_code":"REALITY_BINDING_ACTIVE_CONFIG_FORBIDDEN","expected_stage":"CANONICAL_BOUNDARY","expected_no_write":true}]}
