{"schema_version":"geox_mcft00_negative_fixture_part_v1","phase":"MCFT-00","status":"FROZEN_PENDING_ACCEPTANCE","part_number":4,"fixture_count":10,"fixtures":[{"fixture_id":"NEG_CROP_CONFIG_MISSING","test_kind":"MUTATION","target":"package","mutations":[{"op":"set","path":"config.bindings","value":[{"binding_type":"MODEL_CONFIGURATION_BINDING","binding_version":1,"epistemic_class":"CONFIGURED","spatial_support":"ZONE","vertical_support":"ROOT_ZONE_OR_CROP_PROFILE","source_unit":"mixed_explicit_per_parameter","canonical_unit":"mixed_explicit_per_parameter","conversion_rule":{"id":"PER_PARAMETER_EXPLICIT_UNITS_V1"},"time_semantics":{"effective_from":"MCFT_RUNTIME_CONFIG_ACTIVATION_BOUNDARY","mutable_during_tick":false},"quality_semantics":{"provenance_required":true,"source_version_required":true,"unknown_values_must_be_explicit":true},"availability_semantics":{"resolved_before_tick_compute":true},"eligible_downstream_uses":["MCFT_RUNTIME_CONFIG_COMPILE_INPUT"],"forbidden_downstream_uses":["REALITY_OBSERVATION","DIRECT_STATE_EVIDENCE"],"limitations":["configured authority only","no physical model formula is implemented"],"binding_id":"soil_hydraulic_config_c8_v1","source_role":"SOIL_HYDRAULIC_CONFIGURATION","configuration_source_kind":"VERSIONED_CONFIG_ARTIFACT","configuration_source_id":"mcft_soil_hydraulic_config_c8_v1","configuration_version":1,"quantity_kind":"SOIL_HYDRAULIC_PARAMETER_SET","applicability":{"zone_id":"zone_mcft_c8_water_001","root_zone_definition_id":"rz_c8_0_300mm_v1"},"parameter_provenance":"CONTROLLED_SYNTHETIC_GOVERNED_CONFIG","determinism_hash":"sha256:1f39f16b806ecd02e4f47478635b870f092b25f83d7d69d7820a331f51903b7c"}]}],"expected_reason_code":"CROP_WATER_USE_CONFIGURATION_MISSING","expected_stage":"CONFIG_BINDING_VALIDATION","expected_no_write":true},{"fixture_id":"NEG_CONFIG_SOURCE_VERSION","test_kind":"MUTATION","target":"package","mutations":[{"op":"delete","path":"config.configuration_source_definitions.0.configuration_version"}],"expected_reason_code":"CONFIGURATION_SOURCE_VERSION_MISSING","expected_stage":"CONFIG_BINDING_VALIDATION","expected_no_write":true},{"fixture_id":"NEG_UNKNOWN_DEFAULTED","test_kind":"MUTATION","target":"package","mutations":[{"op":"set","path":"config.configuration_source_definitions.0.parameters.field_capacity_fraction.status","value":"UNKNOWN"}],"expected_reason_code":"UNKNOWN_PARAMETER_HAS_VALUE","expected_stage":"CONFIG_BINDING_VALIDATION","expected_no_write":true},{"fixture_id":"NEG_APPROVED_PLAN_EXECUTED","test_kind":"MUTATION","target":"package","mutations":[{"op":"set","path":"source.bindings.5.action_lifecycle_class","value":"EXECUTION_EVIDENCE"}],"expected_reason_code":"APPROVED_PLAN_MARKED_EXECUTED","expected_stage":"ACTION_SEMANTICS_VALIDATION","expected_no_write":true},{"fixture_id":"NEG_APPROVED_PLAN_STATE_POLICY","test_kind":"MUTATION","target":"package","mutations":[{"op":"set","path":"source.bindings.5.state_input_policy","value":"CONDITIONAL"}],"expected_reason_code":"APPROVED_PLAN_STATE_INPUT_FORBIDDEN","expected_stage":"ACTION_SEMANTICS_VALIDATION","expected_no_write":true},{"fixture_id":"NEG_PLANNED_IRRIGATION_ELIGIBLE","test_kind":"MUTATION","target":"package","mutations":[{"op":"set","path":"source.bindings.5.eligible_for_state_input","value":true}],"expected_reason_code":"PLANNED_IRRIGATION_RECORD_ELIGIBLE_FORBIDDEN","expected_stage":"ACTION_SEMANTICS_VALIDATION","expected_no_write":true},{"fixture_id":"NEG_FEEDBACK_AMOUNT","test_kind":"MUTATION","target":"package","mutations":[{"op":"delete","path":"reality.semantic_payload.action_feedback_eligibility_contract.example_candidate.actual_amount"}],"expected_reason_code":"ACTION_FEEDBACK_ACTUAL_AMOUNT_MISSING","expected_stage":"ACTION_FEEDBACK_VALIDATION","expected_no_write":true},{"fixture_id":"NEG_FEEDBACK_EXECUTED_AT","test_kind":"MUTATION","target":"package","mutations":[{"op":"delete","path":"reality.semantic_payload.action_feedback_eligibility_contract.example_candidate.executed_at"}],"expected_reason_code":"ACTION_FEEDBACK_EXECUTED_AT_MISSING","expected_stage":"ACTION_FEEDBACK_VALIDATION","expected_no_write":true},{"fixture_id":"NEG_FEEDBACK_COVERAGE","test_kind":"MUTATION","target":"package","mutations":[{"op":"delete","path":"reality.semantic_payload.action_feedback_eligibility_contract.example_candidate.spatial_coverage"}],"expected_reason_code":"ACTION_FEEDBACK_SPATIAL_COVERAGE_MISSING","expected_stage":"ACTION_FEEDBACK_VALIDATION","expected_no_write":true},{"fixture_id":"NEG_FEEDBACK_SOURCE_ID","test_kind":"MUTATION","target":"package","mutations":[{"op":"delete","path":"reality.semantic_payload.action_feedback_eligibility_contract.example_candidate.source_identity"}],"expected_reason_code":"ACTION_FEEDBACK_SOURCE_IDENTITY_MISSING","expected_stage":"ACTION_FEEDBACK_VALIDATION","expected_no_write":true}]}
